{
  "theme.base": {
    "//color.background": { "value": "{color.gray.000}" },
    "//color.background.black.bold": { "value": "{color.gray.800}" },
    "//color.background.black.subtle": { "value": "{color.gray.050}" },
    "//color.background.danger": { "value": "{color.red.500}" },
    "//color.background.danger.bold": { "value": "{color.red.600}" },
    "//color.background.danger.hovered": { "value": "{color.red.600}" },
    "//color.background.danger.pressed": { "value": "{color.red.700}" },
    "//color.background.danger.subtle": { "value": "{color.red.100}" },
    "//color.background.disabled.subtler": { "value": "{color.gray.050}" },
    "//color.background.disabled.subtle": { "value": "{color.gray.100}" },
    "//color.background.disabled": { "value": "{color.gray.200}" },
    "//color.background.disabled.bolder": { "value": "{color.gray.400}" },
    "//color.background.gray.subtle": { "value": "{color.gray.050}" },
    "//color.background.gray": { "value": "{color.gray.100}" },
    "//color.background.gray.hovered": { "value": "{color.gray.200}" },
    "//color.background.gray.bold": { "value": "{color.gray.600}" },
    "//color.background.inverse.bold": { "value": "{color.gray.100}" },
    "//color.background.inverse.subtle": { "value": "{color.gray.050}" },
    "//color.background.neutral": { "value": "{color.blue.800}" },
    "//color.background.neutral.hovered": { "value": "{color.gray.900}" },
    "//color.background.neutral.pressed": { "value": "{color.blue.700}" },
    "//color.background.primary": { "value": "{color.blue.500}" },
    "//color.background.primary.bold": { "value": "{color.blue.600}" },
    "//color.background.primary.bolder": { "value": "{color.blue.700}" },
    "//color.background.primary.hovered": { "value": "{color.blue.600}" },
    "//color.background.primary.pressed": { "value": "{color.blue.700}" },
    "//color.background.primary.subtler": { "value": "{color.blue.400}" },
    "//color.background.primary.subtle": { "value": "{color.blue.100}" },
    "//color.background.secondary": { "value": "{color.purple.500}" },
    "//color.background.secondary.bold": { "value": "{color.purple.600}" },
    "//color.background.secondary.hovered": { "value": "{color.purple.600}" },
    "//color.background.secondary.pressed": { "value": "{color.purple.700}" },
    "//color.background.secondary.subtle": { "value": "{color.purple.100}" },
    "//color.background.success": { "value": "{color.green.500}" },
    "//color.background.success.bold": { "value": "{color.green.600}" },
    "//color.background.success.hovered": { "value": "{color.green.600}" },
    "//color.background.success.pressed": { "value": "{color.green.700}" },
    "//color.background.success.subtle": { "value": "{color.green.100}" },
    "//color.background.warning.bold": { "value": "{color.yellow.500}" },
    "//color.background.warning.subtle": { "value": "{color.yellow.300}" },
    "//color.background.underlay": { "value": "{color.blue.800}" },
    "//color.border": { "value": "{color.gray.300}" },
    "//color.border.subtle": { "value": "{color.gray.100}" },
    "//color.border.bolder": { "value": "{color.gray.400}" },
    "//color.border.boldest": { "value": "{color.gray.500}" },
    "//color.border.danger": { "value": "{color.red.500}" },
    "//color.border.danger.bolder": { "value": "{color.red.600}" },
    "//color.border.warning": { "value": "{color.yellow.500}" },
    "//color.border.selected": { "value": "{color.blue.500}" },
    "//color.border.success": { "value": "{color.green.600}" },
    "//color.border.resting": { "value": "{color.gray.200}" },
    "//color.border.incomplete": { "value": "{color.gray.500}" },
    "//color.border.engaged": { "value": "{color.gray.500}" },
    "//color.border.support": { "value": "{color.blue.800}" },
    "//color.border.support.hovered": { "value": "{color.gray.900}" },
    "//color.border.support.pressed": { "value": "{color.gray.700}" },
    "//color.border.inverse": { "value": "{color.gray.000}" },
    "//color.border.inverse.hovered": { "value": "{color.gray.100}" },
    "//color.border.inverse.pressed": { "value": "{color.gray.200}" },
    "//color.border.disabled": { "value": "{color.gray.300}" },
    "//color.border.disabled.subtler": { "value": "{color.gray.200}" },
    "color.scrollbar.thumb": { "value": "{color.gray.500}" },
    "color.scrollbar.track": { "value": "{color.gray.050}" },
    "color.selector": { "value": "{color.green.600}" },
    "color.surface.card.primary": { "value": "{color.gray.000}" },
    "color.surface.card.secondary": { "value": "{color.gray.050}" },
    "color.surface.overlay": { "value": "{color.gray.000}" },
    "color.surface.overlay.hovered": { "value": "{color.gray.050}" },
    "color.separator.primary": { "value": "{color.blue.800}" },
    "color.separator.neutral": { "value": "{color.gray.500}" },
    "color.separator.inverse": { "value": "{color.gray.000}" },
    "color.text": { "value": "{color.blue.800}" },
    "color.text.primary": { "value": "{color.blue.800}" },
    "color.text.action": { "value": "{color.blue.500}" },
    "color.text.subdued": { "value": "{color.gray.600}" },
    "color.text.disabled": { "value": "{color.gray.300}" },
    "color.text.heading": { "value": "{color.blue.800}" },
    "color.text.inverse": { "value": "{color.gray.000}" },
    "color.text.engaged": { "value": "{color.gray.900}" },
    "color.text.gray.resting": { "value": "{color.gray.500}" },
    "color.text.gray.bold": { "value": "{color.gray.800}" },
    "color.text.black.inverse.bold": { "value": "{color.gray.000}" },
    "color.text.black.inverse.subtle": { "value": "{color.blue.800}" },
    "color.text.danger": { "value": "{color.red.600}" },
    "color.text.danger.bold": { "value": "{color.red.800}" },
    "color.text.danger.inverse": { "value": "{color.blue.800}" },
    "color.text.danger.inverse.bold": { "value": "{color.gray.000}" },
    "color.text.danger.inverse.pressed": { "value": "{color.blue.800}" },
    "color.text.danger.inverse.subtle": { "value": "{color.blue.800}" },
    "color.text.gray.inverse.bold": { "value": "{color.gray.000}" },
    "color.text.gray.inverse.subtle": { "value": "{color.blue.800}" },
    "color.text.inverse.inverse.bold": { "value": "{color.gray.900}" },
    "color.text.inverse.inverse.subtle": { "value": "{color.blue.800}" },
    "color.text.primary.inverse": { "value": "{color.gray.000}" },
    "color.text.primary.inverse.bold": { "value": "{color.gray.000}" },
    "color.text.primary.inverse.subtle": { "value": "{color.blue.800}" },
    "color.text.secondary.bold": { "value": "{color.purple.800}" },
    "color.text.secondary.inverse.bold": { "value": "{color.gray.000}" },
    "color.text.secondary.inverse.subtle": { "value": "{color.blue.800}" },
    "color.text.success.bold": { "value": "{color.green.800}" },
    "color.text.success.inverse": { "value": "{color.blue.800}" },
    "color.text.success.inverse.bold": { "value": "{color.gray.000}" },
    "color.text.success.inverse.subtle": { "value": "{color.blue.800}" },
    "color.text.success.inverse.pressed": { "value": "{color.gray.000}" },
    "color.text.warning.inverse.bold": { "value": "{color.gray.900}" },
    "color.text.warning.inverse.subtle": { "value": "{color.blue.800}" },
    "color.text.code.base": { "value": "{color.blue.800}" },
    "color.text.code.lineNumber": { "value": "{color.gray.600}" },
    "color.text.code.comment": { "value": "{color.gray.400}" },
    "color.text.code.punctuation": { "value": "{color.gray.700}" },
    "color.text.code.property": { "value": "{color.red.700}" },
    "color.text.code.selector": { "value": "{color.green.700}" },
    "color.text.code.operator": { "value": "{color.yellow.800}" },
    "color.text.code.variable": { "value": "{color.yellow.700}" },
    "color.text.code.function": { "value": "{color.red.600}" },
    "color.text.code.keyword": { "value": "{color.blue.500}" },
    "color.primary.800": { "value": "{color.blue.800}" },
    "color.primary.700": { "value": "{color.blue.700}" },
    "color.primary.600": { "value": "{color.blue.600}" },
    "color.primary.500": { "value": "{color.blue.500}" },
    "color.primary.400": { "value": "{color.blue.400}" },
    "color.primary.300": { "value": "{color.blue.300}" },
    "color.primary.200": { "value": "{color.blue.200}" },
    "color.primary.100": { "value": "{color.blue.100}" },
    "color.secondary.800": { "value": "{color.purple.800}" },
    "color.secondary.700": { "value": "{color.purple.700}" },
    "color.secondary.600": { "value": "{color.purple.600}" },
    "color.secondary.500": { "value": "{color.purple.500}" },
    "color.secondary.400": { "value": "{color.purple.400}" },
    "color.secondary.300": { "value": "{color.purple.300}" },
    "color.secondary.200": { "value": "{color.purple.200}" },
    "color.secondary.100": { "value": "{color.purple.100}" },
    "color.positive.800": { "value": "{color.green.800}" },
    "color.positive.700": { "value": "{color.green.700}" },
    "color.positive.600": { "value": "{color.green.600}" },
    "color.positive.500": { "value": "{color.green.500}" },
    "color.positive.400": { "value": "{color.green.400}" },
    "color.positive.300": { "value": "{color.green.300}" },
    "color.positive.200": { "value": "{color.green.200}" },
    "color.positive.100": { "value": "{color.green.100}" },
    "color.negative.800": { "value": "{color.red.800}" },
    "color.negative.700": { "value": "{color.red.700}" },
    "color.negative.600": { "value": "{color.red.600}" },
    "color.negative.500": { "value": "{color.red.500}" },
    "color.negative.400": { "value": "{color.red.400}" },
    "color.negative.300": { "value": "{color.red.300}" },
    "color.negative.200": { "value": "{color.red.200}" },
    "color.negative.100": { "value": "{color.red.100}" },
    "color.warning.800": { "value": "{color.yellow.800}" },
    "color.warning.700": { "value": "{color.yellow.700}" },
    "color.warning.600": { "value": "{color.yellow.600}" },
    "color.warning.500": { "value": "{color.yellow.500}" },
    "color.warning.400": { "value": "{color.yellow.400}" },
    "color.warning.300": { "value": "{color.yellow.300}" },
    "color.warning.200": { "value": "{color.yellow.200}" },
    "color.warning.100": { "value": "{color.yellow.100}" },
    "color.neutral.900": { "value": "{color.gray.900}" },
    "color.neutral.800": { "value": "{color.gray.800}" },
    "color.neutral.700": { "value": "{color.gray.700}" },
    "color.neutral.600": { "value": "{color.gray.600}" },
    "color.neutral.500": { "value": "{color.gray.500}" },
    "color.neutral.400": { "value": "{color.gray.400}" },
    "color.neutral.300": { "value": "{color.gray.300}" },
    "color.neutral.200": { "value": "{color.gray.200}" },
    "color.neutral.100": { "value": "{color.gray.100}" },
    "color.neutral.050": { "value": "{color.gray.050}" },
    "color.neutral.000": { "value": "{color.gray.000}" },
    "font.family": { "value": "{font.family.sans}" },
    "shadow.button": { "value": "{shadow.button}" },
    "shadow.overlay": { "value": "{shadow.overlay}" },
    "shadow.overlay.subdued": { "value": "{shadow.overlay_subdued}" }
  }
}
